msu_ssc/__init__.py
msu_ssc/path_util.py
msu_ssc/prompt_util.py
msu_ssc/ssc_log.py
msu_ssc/time_util.py
msu_ssc/udp_mux.py
msu_ssc/udp_proxy.py
msu_ssc-2.0.1.dist-info/licenses/LICENSE
msu_ssc-2.0.1.dist-info/METADATA
msu_ssc-2.0.1.dist-info/WHEEL
msu_ssc-2.0.1.dist-info/top_level.txt
msu_ssc-2.0.1.dist-info/RECORD
