Metadata-Version: 2.4
Name: msu-ssc
Version: 2.0.1
Summary: Morehead State University Space Science Center utilities
Author-email: David Mayo <dcmayo@moreheadstate.edu>
License-Expression: MIT
Project-URL: homepage, https://github.com/msu-ssc/msu-ssc
Requires-Python: >=3.7
License-File: LICENSE
Requires-Dist: python-json-logger>=3.0.1
Requires-Dist: rich>=13.8.1
Dynamic: license-file
